LICENSE
MANIFEST.in
README.md
README.pypi
pyproject.toml
requirements.txt
setup.py
Orange3_core_extended.egg-info/PKG-INFO
Orange3_core_extended.egg-info/SOURCES.txt
Orange3_core_extended.egg-info/dependency_links.txt
Orange3_core_extended.egg-info/entry_points.txt
Orange3_core_extended.egg-info/namespace_packages.txt
Orange3_core_extended.egg-info/not-zip-safe
Orange3_core_extended.egg-info/requires.txt
Orange3_core_extended.egg-info/top_level.txt
orangecontrib/__init__.py
orangecontrib/core_extended/__init__.py
orangecontrib/core_extended/widgets/__init__.py
orangecontrib/core_extended/widgets/owhistogram.py
orangecontrib/core_extended/widgets/owimproveddistances.py
orangecontrib/core_extended/widgets/owtransposecolumn.py
orangecontrib/core_extended/widgets/components/__init__.py
orangecontrib/core_extended/widgets/components/widgets/__init__.py
orangecontrib/core_extended/widgets/components/widgets/intlineedit.py
orangecontrib/core_extended/widgets/icons/category.svg
orangecontrib/core_extended/widgets/icons/histogram.svg
orangecontrib/core_extended/widgets/icons/improved_distances.svg
orangecontrib/core_extended/widgets/icons/transpose_column.svg